{
	"main": {
		"title": { "ru": "Основные параметры" },
		"icon": "",
		"param": {
			"mobile": {
				"title": { "ru": "Звонки" },
				"unit": { "ru": "минут/день" },
				"icon": "",
				"default": "20",
				"option": {
					"20": { "title": "20", "cost": 1 },
					"40": { "title": "40", "cost": 2 },
					"60": { "title": "60", "cost": 3 },
					"120": { "title": "120", "cost": 4 }
				}
			},
			"internet": {
				"title": { "ru": "Интернет" },
				"unit": { "ru": "мегабайт/день" },
				"icon": "",
				"default": "100",
				"option": {
					"100": { "title": "100", "cost": 1 },
					"500": { "title": "500", "cost": 2 },
					"1000": { "title": "1000", "cost": 3 },
					"2000": { "title": "2000", "cost": 4 }
				}
			}
		}
	},
	"unlim": {
		"title": { "ru": "Безлимиты" },
		"icon": "",
		"param": {
			"social": {
				"title": { "ru": "Социальные сети" },
				"icon": "",
				"cost": 5
			},
			"messanger": {
				"title": { "ru": "Менссенджеры" },
				"icon": "",
				"cost": 5
			},
			"video": {
				"title": { "ru": "Видеохостинги" },
				"icon": "",
				"cost": 5
			}
		}
	}
}
